aidot/__init__.py
aidot/aes_utils.py
aidot/discover.py
aidot/lan.py
aidot/login_const.py
aidot/login_control.py
aidot/login_data.py
python_aidot-0.1.2.dist-info/LICENSE
python_aidot-0.1.2.dist-info/METADATA
python_aidot-0.1.2.dist-info/WHEEL
python_aidot-0.1.2.dist-info/top_level.txt
python_aidot-0.1.2.dist-info/RECORD
