Metadata-Version: 2.1
Name: python-aidot
Version: 0.1.2
Summary: aidot control wifi lights
Home-page: https://github.com/Aidot-Development-Team/python-aidot
Author: aidotdev2024
Classifier: Programming Language :: Python :: 3.11
Classifier: License :: OSI Approved :: MIT License
Classifier: Operating System :: OS Independent
License-File: LICENSE
Requires-Dist: requests
Requires-Dist: aiohttp
Requires-Dist: setuptools
